aidbox_python_sdk/__init__.py
aidbox_python_sdk/aidboxpy.py
aidbox_python_sdk/app_keys.py
aidbox_python_sdk/db.py
aidbox_python_sdk/db_migrations.py
aidbox_python_sdk/exceptions.py
aidbox_python_sdk/handlers.py
aidbox_python_sdk/main.py
aidbox_python_sdk/py.typed
aidbox_python_sdk/pytest_plugin.py
aidbox_python_sdk/sdk.py
aidbox_python_sdk/settings.py
aidbox_python_sdk/types.py
aidbox_python_sdk-0.1.21.dist-info/licenses/LICENSE.md
aidbox_python_sdk-0.1.21.dist-info/METADATA
aidbox_python_sdk-0.1.21.dist-info/WHEEL
aidbox_python_sdk-0.1.21.dist-info/top_level.txt
aidbox_python_sdk-0.1.21.dist-info/RECORD
