Metadata-Version: 2.4
Name: aidbox-python-sdk
Version: 0.1.21
Summary: Aidbox SDK for python
Author-email: "beda.software" <aidbox-python-sdk@beda.software>
License: MIT License
Project-URL: homepage, https://github.com/Aidbox/aidbox-python-sdk
Project-URL: documentation, https://github.com/Aidbox/aidbox-python-sdk#readme
Project-URL: repository, https://github.com/Aidbox/aidbox-python-sdk.git
Keywords: fhir
Classifier: Development Status :: 5 - Production/Stable
Classifier: Environment :: Web Environment
Classifier: Intended Audience :: Developers
Classifier: Operating System :: OS Independent
Classifier: Programming Language :: Python
Classifier: Programming Language :: Python :: 3
Classifier: Programming Language :: Python :: 3.9
Classifier: Programming Language :: Python :: 3.10
Classifier: Programming Language :: Python :: 3.11
Classifier: Programming Language :: Python :: 3.12
Classifier: Topic :: Internet :: WWW/HTTP
Classifier: Topic :: Software Development :: Libraries :: Python Modules
Requires-Python: >=3.8
License-File: LICENSE.md
Requires-Dist: aiohttp>=3.11.0
Requires-Dist: SQLAlchemy>=1.3.10
Requires-Dist: fhirpy>=1.3.0
Requires-Dist: jsonschema>=4.4.0
Provides-Extra: test
Requires-Dist: pytest~=8.4.1; extra == "test"
Requires-Dist: pytest-asyncio~=1.1.0; extra == "test"
Requires-Dist: pytest-aiohttp~=1.1.0; extra == "test"
Requires-Dist: pytest-cov~=6.2.1; extra == "test"
Provides-Extra: dev
Requires-Dist: black; extra == "dev"
Requires-Dist: autohooks; extra == "dev"
Requires-Dist: autohooks-plugin-ruff; extra == "dev"
Requires-Dist: autohooks-plugin-black; extra == "dev"
Dynamic: license-file
